README
setup.py
scriptharness/__init__.py
scriptharness/actions.py
scriptharness/commands.py
scriptharness/config.py
scriptharness/errorlists.py
scriptharness/exceptions.py
scriptharness/log.py
scriptharness/os.py
scriptharness/process.py
scriptharness/script.py
scriptharness/status.py
scriptharness/structures.py
scriptharness/unicode.py
scriptharness/version.py
scriptharness.egg-info/PKG-INFO
scriptharness.egg-info/SOURCES.txt
scriptharness.egg-info/dependency_links.txt
scriptharness.egg-info/entry_points.txt
scriptharness.egg-info/not-zip-safe
scriptharness.egg-info/requires.txt
scriptharness.egg-info/top_level.txt