Metadata-Version: 1.1
Name: scriptharness
Version: 0.2.0
Summary: A generic logging, configuration, and workflow framework for scripts.
Home-page: https://github.com/scriptharness/scriptharness
Author: Aki Sasaki
Author-email: aki@escapewindow.com
License: MPL2
Platform: Posix
Platform: MacOS X
Platform: Windows
Classifier: Development Status :: 3 - Alpha
Classifier: Intended Audience :: Developers
Classifier: Natural Language :: English
Classifier: Operating System :: MacOS :: MacOS X
Classifier: Operating System :: Microsoft :: Windows
Classifier: Operating System :: POSIX
Classifier: Operating System :: POSIX :: BSD
Classifier: Operating System :: POSIX :: Linux
Classifier: Topic :: Software Development
Classifier: Programming Language :: Python :: 2
Classifier: Programming Language :: Python :: 2.7
Classifier: Programming Language :: Python :: 3
Classifier: Programming Language :: Python :: 3.3
Classifier: Programming Language :: Python :: 3.4
Classifier: Programming Language :: Python :: Implementation :: PyPy
